imlab/__init__.py
imlab/__main__.py
imlab/classifier.py
imlab/classifier_wrapper.py
imlab/core.py
imlab/extractor.py
imlab/extractor_wrapper.py
imlab/picture.py
imlab/tools.py
imlab/train_classifier.py
imlab/train_classifier_old.py
imlab/train_extractor.py
imlab/font/FUTURAM.ttf
imlab/model/yoloV7_coco.extractor
imlab/yolo/__init__.py
imlab/yolo/coco_classes.py
imlab/yolo/models.py
imlab/yolo/utils.py
imlab/yolo/yoloV7.json
imlab/yolo/yolov7.py
imlab-0.52.dist-info/LICENSE.md
imlab-0.52.dist-info/METADATA
imlab-0.52.dist-info/WHEEL
imlab-0.52.dist-info/entry_points.txt
imlab-0.52.dist-info/top_level.txt
imlab-0.52.dist-info/RECORD
